diskcache/__init__.py
diskcache/cli.py
diskcache/core.py
diskcache/djangocache.py
diskcache/fanout.py
diskcache/persistent.py
diskcache/recipes.py
diskcache-5.6.0.dist-info/LICENSE
diskcache-5.6.0.dist-info/METADATA
diskcache-5.6.0.dist-info/WHEEL
diskcache-5.6.0.dist-info/top_level.txt
diskcache-5.6.0.dist-info/RECORD
