Metadata-Version: 2.1
Name: diskcache
Version: 5.6.0
Summary: Disk Cache -- Disk and file backed persistent cache.
Home-page: http://www.grantjenks.com/docs/diskcache/
Author: Grant Jenks
Author-email: contact@grantjenks.com
License: Apache 2.0
Project-URL: Documentation, http://www.grantjenks.com/docs/diskcache/
Project-URL: Funding, https://gum.co/diskcache
Project-URL: Source, https://github.com/grantjenks/python-diskcache
Project-URL: Tracker, https://github.com/grantjenks/python-diskcache/issues
Classifier: Development Status :: 5 - Production/Stable
Classifier: Intended Audience :: Developers
Classifier: License :: OSI Approved :: Apache Software License
Classifier: Natural Language :: English
Classifier: Programming Language :: Python
Classifier: Programming Language :: Python :: 3
Classifier: Programming Language :: Python :: 3.5
Classifier: Programming Language :: Python :: 3.6
Classifier: Programming Language :: Python :: 3.7
Classifier: Programming Language :: Python :: 3.8
Classifier: Programming Language :: Python :: 3.9
Classifier: Programming Language :: Python :: Implementation :: CPython
Requires-Python: >=3
License-File: LICENSE
